README.md
setup.py
mockfly/__init__.py
mockfly_python_sdk.egg-info/PKG-INFO
mockfly_python_sdk.egg-info/SOURCES.txt
mockfly_python_sdk.egg-info/dependency_links.txt
mockfly_python_sdk.egg-info/requires.txt
mockfly_python_sdk.egg-info/top_level.txt