Metadata-Version: 2.1
Name: mockfly-python-sdk
Version: 0.0.1
Summary: Mockfly SDK for Python
Home-page: https://github.com/Mockfly-Dev/mockfly-python-sdk.git
Author: Mockfly
Author-email: mockflydev@gmail.com
License: UNKNOWN
Platform: UNKNOWN
